regens.py
regens_library.py
regens_testers.py
regens-0.2.0.dist-info/LICENSE.md
regens-0.2.0.dist-info/METADATA
regens-0.2.0.dist-info/WHEEL
regens-0.2.0.dist-info/entry_points.txt
regens-0.2.0.dist-info/top_level.txt
regens-0.2.0.dist-info/RECORD
