Metadata-Version: 2.1
Name: regens
Version: 0.2.0
Summary: UNKNOWN
Home-page: UNKNOWN
License: UNKNOWN
Platform: UNKNOWN
Requires-Python: ==3.7.*
Requires-Dist: bed-reader (==0.1.1)
Requires-Dist: numpy (==1.16.2)
Requires-Dist: pandas (==1.1.2)
Requires-Dist: matplotlib (==3.0.3)
Requires-Dist: scipy (==1.2.1)
Requires-Dist: scikit-learn (==0.20.3)
